enochecker_core/__init__.py
enochecker_core/py.typed
enochecker_core-0.13.0.dist-info/licenses/LICENSE
enochecker_core-0.13.0.dist-info/METADATA
enochecker_core-0.13.0.dist-info/WHEEL
enochecker_core-0.13.0.dist-info/top_level.txt
enochecker_core-0.13.0.dist-info/RECORD
