Metadata-Version: 2.4
Name: enochecker-core
Version: 0.13.0
Summary: Library for enochecker data structures
Author-email: Louis Burda <dev@sinitax.com>, Trolldemorted <benediktradtke@gmail.com>
Requires-Python: >=3.10
License-File: LICENSE
Requires-Dist: pydantic>=2.11.7
Dynamic: license-file
